nomadenv/__init__.py
nomadenv/__main__.py
nomadenv/__version__.py
nomadenv/nomadenv.py
nomadenv/pyenv.py
nomadenv/resources/sitecustomize.py
nomadenv/resources/test_scriptmaker.py
nomadenv/utils.py
nomadenv-0.1.5.dist-info/entry_points.txt
nomadenv-0.1.5.dist-info/LICENSE
nomadenv-0.1.5.dist-info/WHEEL
nomadenv-0.1.5.dist-info/METADATA
nomadenv-0.1.5.dist-info/RECORD
